EasyFEA/__about__.py
EasyFEA/__init__.py
EasyFEA/FEM/__init__.py
EasyFEA/FEM/_boundary_conditions.py
EasyFEA/FEM/_field.py
EasyFEA/FEM/_forms.py
EasyFEA/FEM/_gauss.py
EasyFEA/FEM/_group_elem.py
EasyFEA/FEM/_linalg.py
EasyFEA/FEM/_mesh.py
EasyFEA/FEM/_mesher.py
EasyFEA/FEM/_utils.py
EasyFEA/FEM/Elems/__init__.py
EasyFEA/FEM/Elems/_hexa.py
EasyFEA/FEM/Elems/_point.py
EasyFEA/FEM/Elems/_prism.py
EasyFEA/FEM/Elems/_quad.py
EasyFEA/FEM/Elems/_seg.py
EasyFEA/FEM/Elems/_tetra.py
EasyFEA/FEM/Elems/_tri.py
EasyFEA/Geoms/__init__.py
EasyFEA/Geoms/_circle.py
EasyFEA/Geoms/_contour.py
EasyFEA/Geoms/_domain.py
EasyFEA/Geoms/_geom.py
EasyFEA/Geoms/_line.py
EasyFEA/Geoms/_points.py
EasyFEA/Geoms/_utils.py
EasyFEA/Models/__init__.py
EasyFEA/Models/_phasefield.py
EasyFEA/Models/_thermal.py
EasyFEA/Models/_utils.py
EasyFEA/Models/_weakforms.py
EasyFEA/Models/Beam/__init__.py
EasyFEA/Models/Beam/_beam.py
EasyFEA/Models/Elastic/__init__.py
EasyFEA/Models/Elastic/_laws.py
EasyFEA/Models/HyperElastic/__init__.py
EasyFEA/Models/HyperElastic/_laws.py
EasyFEA/Models/HyperElastic/_state.py
EasyFEA/Simulations/Solvers.py
EasyFEA/Simulations/__init__.py
EasyFEA/Simulations/_beam.py
EasyFEA/Simulations/_dic.py
EasyFEA/Simulations/_elastic.py
EasyFEA/Simulations/_hyperelastic.py
EasyFEA/Simulations/_phasefield.py
EasyFEA/Simulations/_simu.py
EasyFEA/Simulations/_thermal.py
EasyFEA/Simulations/_utils.py
EasyFEA/Simulations/_weakforms.py
EasyFEA/Utilities/Display.py
EasyFEA/Utilities/Folder.py
EasyFEA/Utilities/MeshIO.py
EasyFEA/Utilities/Numba.py
EasyFEA/Utilities/Paraview.py
EasyFEA/Utilities/PyVista.py
EasyFEA/Utilities/Vizir.py
EasyFEA/Utilities/__init__.py
EasyFEA/Utilities/_cache.py
EasyFEA/Utilities/_observers.py
EasyFEA/Utilities/_params.py
EasyFEA/Utilities/_requires.py
EasyFEA/Utilities/_tic.py
EasyFEA/Utilities/_types.py
easyfea-1.7.1.dist-info/licenses/AUTHORS.md
easyfea-1.7.1.dist-info/licenses/LICENSE.txt
easyfea-1.7.1.dist-info/METADATA
easyfea-1.7.1.dist-info/WHEEL
easyfea-1.7.1.dist-info/top_level.txt
easyfea-1.7.1.dist-info/RECORD
