Metadata-Version: 2.4
Name: easyfea
Version: 1.7.1
Summary: User-friendly Python library that simplifies finite element analysis.
Author-email: Matthieu Noel <matthieu.noel7@gmail.com>
License:                     GNU GENERAL PUBLIC LICENSE
Project-URL: Documentation, https://easyfea.readthedocs.io/en/latest/
Project-URL: Repository, https://github.com/matnoel/EasyFEA
Project-URL: Issues, https://github.com/matnoel/EasyFEA/issues
Project-URL: Changelog, https://github.com/matnoel/EasyFEA/blob/main/CHANGELOG.md
Keywords: finite-element-analysis,phase-field,python,easy,fem
Classifier: Intended Audience :: Science/Research
Classifier: Topic :: Scientific/Engineering
Classifier: License :: OSI Approved :: GNU General Public License v3 (GPLv3)
Classifier: Operating System :: MacOS :: MacOS X
Classifier: Operating System :: Microsoft :: Windows
Classifier: Operating System :: POSIX :: Linux
Classifier: Programming Language :: Python :: 3.9
Classifier: Programming Language :: Python :: 3.10
Classifier: Programming Language :: Python :: 3.11
Classifier: Programming Language :: Python :: 3.12
Classifier: Programming Language :: Python :: 3.13
Requires-Python: >=3.9
License-File: LICENSE.txt
License-File: AUTHORS.md
Requires-Dist: numpy
Requires-Dist: gmsh>=4.12
Requires-Dist: scipy
Provides-Extra: dev
Requires-Dist: mypy; extra == "dev"
Requires-Dist: black; extra == "dev"
Requires-Dist: ruff; extra == "dev"
Requires-Dist: pytest; extra == "dev"
Provides-Extra: io
Requires-Dist: imageio; extra == "io"
Requires-Dist: imageio[ffmpeg]; extra == "io"
Requires-Dist: meshio; extra == "io"
Provides-Extra: viz
Requires-Dist: matplotlib; extra == "viz"
Requires-Dist: pyvista; extra == "viz"
Dynamic: license-file
